LICENSE
autoretouchlib/__init__.py
autoretouchlib/auth.py
autoretouchlib/caching.py
autoretouchlib/container_memory.py
autoretouchlib/logging.py
autoretouchlib/metrics.py
autoretouchlib/mock/__init__.py
autoretouchlib/mock/aiproxy.py
autoretouchlib/mock/storage.py
autoretouchlib/mock/storage_utils.py
autoretouchlib/mock/tracing.py
autoretouchlib/prediction_service.py
autoretouchlib/storage.py
autoretouchlib/storage_v2.py
autoretouchlib/tracing.py
autoretouchlib/types.py
autoretouch_service_library-2.3.29.dist-info/LICENSE
autoretouch_service_library-2.3.29.dist-info/WHEEL
autoretouch_service_library-2.3.29.dist-info/METADATA
autoretouch_service_library-2.3.29.dist-info/RECORD
