Metadata-Version: 2.1
Name: autoretouch-service-library
Version: 2.3.29
Summary: Autoretouch helper library
Author: Till Lorentzen
Author-email: till@autoretouch.com
Requires-Python: >=3.7,<4.0
Classifier: Programming Language :: Python :: 3
Classifier: Programming Language :: Python :: 3.7
Classifier: Programming Language :: Python :: 3.8
Classifier: Programming Language :: Python :: 3.9
Classifier: Programming Language :: Python :: 3.10
Classifier: Programming Language :: Python :: 3.11
Requires-Dist: canonicaljson (>=1.3.0,<2.0.0)
Requires-Dist: fakeredis (==1.6.1)
Requires-Dist: fastapi (>=0.65.1,<0.66.0)
Requires-Dist: google-cloud-storage (>=1.42.3)
Requires-Dist: grpcio (>=1.41.0)
Requires-Dist: opencensus (>=0.7.13)
Requires-Dist: opencensus-ext-stackdriver (>=0.8.0)
Requires-Dist: psutil (>=5.8.0)
Requires-Dist: redis (>=3.5.3,<4.0.0)
Requires-Dist: requests_mock (>=1.8.0,<2.0.0)
Requires-Dist: retry (==0.9.2)
